openedx_plugin/__about__.py
openedx_plugin/__init__.py
openedx_plugin/admin.py
openedx_plugin/apps.py
openedx_plugin/middleware.py
openedx_plugin/models.py
openedx_plugin/signals.py
openedx_plugin/urls.py
openedx_plugin/utils.py
openedx_plugin/waffle.py
openedx_plugin/wordpress_oauth2_backend.py
openedx_plugin/api/__init__.py
openedx_plugin/api/serializers.py
openedx_plugin/api/urls.py
openedx_plugin/api/views.py
openedx_plugin/dashboard/__init__.py
openedx_plugin/dashboard/utils.py
openedx_plugin/dashboard/views.py
openedx_plugin/locale/__init__.py
openedx_plugin/locale/utils.py
openedx_plugin/locale/views.py
openedx_plugin/management/__init__.py
openedx_plugin/management/commands/__init__.py
openedx_plugin/management/commands/openedx_plugin_init.py
openedx_plugin/migrations/0001_initial.py
openedx_plugin/migrations/0002_alter_marketingsites_language.py
openedx_plugin/migrations/__init__.py
openedx_plugin/settings/__init__.py
openedx_plugin/settings/common.py
openedx_plugin/settings/production.py
openedx_plugin_api/__about__.py
openedx_plugin_api/__init__.py
openedx_plugin_api/admin.py
openedx_plugin_api/api.py
openedx_plugin_api/apps.py
openedx_plugin_api/models.py
openedx_plugin_api/signals.py
openedx_plugin_api/urls.py
openedx_plugin_api/utils.py
openedx_plugin_api/waffle.py
openedx_plugin_api/management/__init__.py
openedx_plugin_api/management/commands/__init__.py
openedx_plugin_api/management/commands/create_oauth_application_client_config.py
openedx_plugin_api/management/commands/openedx_plugin_api_init.py
openedx_plugin_api/migrations/0001_initial.py
openedx_plugin_api/migrations/__init__.py
openedx_plugin_api/settings/__init__.py
openedx_plugin_api/settings/production.py
openedx_plugin_api/tests/__init__.py
openedx_plugin_api/tests/test_edxapi_endpoints.py
openedx_plugin_cms/__about__.py
openedx_plugin_cms/__init__.py
openedx_plugin_cms/admin.py
openedx_plugin_cms/apps.py
openedx_plugin_cms/auditor.py
openedx_plugin_cms/models.py
openedx_plugin_example-0.2.1.dist-info/LICENSE.txt
openedx_plugin_example-0.2.1.dist-info/METADATA
openedx_plugin_example-0.2.1.dist-info/WHEEL
openedx_plugin_example-0.2.1.dist-info/entry_points.txt
openedx_plugin_example-0.2.1.dist-info/top_level.txt
openedx_plugin_example-0.2.1.dist-info/RECORD
