Metadata-Version: 2.1
Name: openedx-plugin-example
Version: 0.2.1
Summary: A Django plugin to modify and enhance the feature set of the Open edX learning management system
Home-page: https://github.com/cookiecutter-openedx/example-openedx-plugin
Download-URL: https://github.com/cookiecutter-openedx/cookiecutter-openedx-devops.git
Author: Lawrence McDaniel
Author-email: Lawrence McDaniel <lpm0073@gmail.com>
License: GNU AFFERO GENERAL PUBLIC LICENSE
Project-URL: Homepage, https://github.com/cookiecutter-openedx/openedx-plugin-example
Project-URL: Documentation, https://github.com/cookiecutter-openedx/openedx-plugin-example
Project-URL: Repository, https://github.com/cookiecutter-openedx/openedx-plugin-example
Project-URL: Changelog, https://github.com/cookiecutter-openedx/openedx-plugin-example/blob/main/CHANGELOG.md
Project-URL: Bug Tracker, https://github.com/cookiecutter-openedx/openedx-plugin-example/issues
Keywords: Python,Django,Open edX,Plugin,REST API
Classifier: Development Status :: 4 - Beta
Classifier: Framework :: Django
Classifier: Framework :: Django :: 2.2
Classifier: Framework :: Django :: 3.0
Classifier: Framework :: Django :: 3.1
Classifier: Framework :: Django :: 3.2
Classifier: Intended Audience :: Developers
Classifier: License :: OSI Approved :: GNU Affero General Public License v3 or later (AGPLv3+)
Classifier: Natural Language :: English
Classifier: Operating System :: OS Independent
Classifier: Programming Language :: Python :: 3
Classifier: Programming Language :: Python :: 3.7
Classifier: Programming Language :: Python :: 3.8
Classifier: Topic :: Education
Classifier: Topic :: Education :: Computer Aided Instruction (CAI)
Requires-Python: >=3.8
License-File: LICENSE.txt
Requires-Dist: Django (<=3.3,>=3.2)
Requires-Dist: validators
Requires-Dist: django-environ
Provides-Extra: django
Requires-Dist: Django (>=3.2) ; extra == 'django'
Provides-Extra: local
Requires-Dist: pre-commit ; extra == 'local'
Requires-Dist: black ; extra == 'local'
Requires-Dist: flake8 ; extra == 'local'
Requires-Dist: ipython ; extra == 'local'
